ublackdev/__init__.py
ublackdev/versions.py
ublackdev-1.1.dist-info/METADATA
ublackdev-1.1.dist-info/WHEEL
ublackdev-1.1.dist-info/top_level.txt
ublackdev-1.1.dist-info/RECORD
