Metadata-Version: 2.1
Name: ublackdev
Version: 1.1
Summary: A Secure and Powerful Python-Telethon Based Library For Userbot.
Home-page: https://github.com/ilhammansiz
Author: ilhammansiz
Author-email: ilhammansiz225@gmail.com
License: GNU AFFERO GENERAL PUBLIC LICENSE (v3)
Classifier: Programming Language :: Python :: 3
Classifier: License :: OSI Approved :: GNU General Public License v3 (GPLv3)
Classifier: Operating System :: OS Independent
Requires-Python: >=3.6
Requires-Dist: aiofiles
Requires-Dist: aiohttp
